MANIFEST.in
README.md
pyproject.toml
setup.py
py3grok/__init__.py
py3grok/py3grok.py
py3grok.egg-info/PKG-INFO
py3grok.egg-info/SOURCES.txt
py3grok.egg-info/dependency_links.txt
py3grok.egg-info/requires.txt
py3grok.egg-info/top_level.txt
py3grok/patterns/aws
py3grok/patterns/bacula
py3grok/patterns/bind
py3grok/patterns/bro
py3grok/patterns/exim
py3grok/patterns/firewalls
py3grok/patterns/grok-patterns
py3grok/patterns/haproxy
py3grok/patterns/httpd
py3grok/patterns/java
py3grok/patterns/junos
py3grok/patterns/linux-syslog
py3grok/patterns/maven
py3grok/patterns/mcollective
py3grok/patterns/mongodb
py3grok/patterns/nagios
py3grok/patterns/postgresql
py3grok/patterns/rails
py3grok/patterns/redis
py3grok/patterns/ruby
py3grok/patterns/squid
py3grok/patterns/zeek