Metadata-Version: 2.1
Name: py3grok
Version: 0.2.0
Summary: Parse strings and extract information from structured or unstructured data.
Home-page: https://github.com/ztroop/py3grok
Author: Zackary Troop
License: MIT
Platform: UNKNOWN
Classifier: Intended Audience :: Developers
Classifier: Operating System :: OS Independent
Classifier: Programming Language :: Python :: 3
Requires-Python: >=3.7.*
